skalds/__init__.py
skalds/skald.py
skalds/config/__init__.py
skalds/config/_enum.py
skalds/config/skald_config.py
skalds/config/system_controller_config.py
skalds/config/systemconfig.py
skalds/handler/__init__.py
skalds/handler/survive.py
skalds/model/__init__.py
skalds/model/event.py
skalds/model/task.py
skalds/proxy/kafka.py
skalds/proxy/mongo.py
skalds/proxy/redis.py
skalds/repository/repository.py
skalds/store/__init__.py
skalds/store/taskworker.py
skalds/system_controller/__init__.py
skalds/system_controller/main.py
skalds/system_controller/api/__init__.py
skalds/system_controller/api/models.py
skalds/system_controller/api/server.py
skalds/system_controller/api/endpoints/__init__.py
skalds/system_controller/api/endpoints/events.py
skalds/system_controller/api/endpoints/skalds.py
skalds/system_controller/api/endpoints/system.py
skalds/system_controller/api/endpoints/tasks.py
skalds/system_controller/monitor/__init__.py
skalds/system_controller/monitor/dispatcher.py
skalds/system_controller/monitor/skald_monitor.py
skalds/system_controller/monitor/task_monitor.py
skalds/system_controller/service/__init__.py
skalds/system_controller/service/summary_service.py
skalds/system_controller/static/dashboard/index.html
skalds/system_controller/static/dashboard/assets/index-2No7GYAS.css
skalds/system_controller/static/dashboard/assets/index-B7U4dIS2.js
skalds/system_controller/static/dashboard/assets/index-B7U4dIS2.js.map
skalds/system_controller/static/dashboard/assets/query-C6o_FDNk.js
skalds/system_controller/static/dashboard/assets/query-C6o_FDNk.js.map
skalds/system_controller/static/dashboard/assets/router-jua2Vyaz.js
skalds/system_controller/static/dashboard/assets/router-jua2Vyaz.js.map
skalds/system_controller/static/dashboard/assets/table-iqIhI9LJ.js
skalds/system_controller/static/dashboard/assets/table-iqIhI9LJ.js.map
skalds/system_controller/static/dashboard/assets/vendor-Gm9i_4Ku.js
skalds/system_controller/static/dashboard/assets/vendor-Gm9i_4Ku.js.map
skalds-0.3.7.dist-info/licenses/LICENSE
skalds-0.3.7.dist-info/METADATA
skalds-0.3.7.dist-info/WHEEL
skalds-0.3.7.dist-info/top_level.txt
skalds-0.3.7.dist-info/RECORD
