Metadata-Version: 2.4
Name: skalds
Version: 0.3.7
Summary: An event-driven, modular distributed task scheduling and execution system.
Author: JiHungLin
License: MIT License
Project-URL: Homepage, https://github.com/JiHungLin/skalds
Project-URL: Bug Tracker, https://github.com/JiHungLin/skalds/issues
Classifier: Programming Language :: Python :: 3
Classifier: Programming Language :: Python :: 3.11
Classifier: License :: OSI Approved :: MIT License
Classifier: Operating System :: OS Independent
Classifier: Intended Audience :: Developers
Classifier: Topic :: Software Development :: Libraries
Classifier: Topic :: System :: Distributed Computing
Requires-Python: >=3.11
License-File: LICENSE
Requires-Dist: pydantic>=2.5.0
Requires-Dist: kafka-python==2.2.7
Requires-Dist: redis==6.1.0
Requires-Dist: pymongo==4.14.0
Requires-Dist: pretty-loguru>=1.1.2
Requires-Dist: python-dotenv==1.1.1
Requires-Dist: ruamel.yaml==0.18.10
Provides-Extra: dev
Requires-Dist: pytest>=7.4.0; extra == "dev"
Provides-Extra: backend
Requires-Dist: fastapi; extra == "backend"
Requires-Dist: uvicorn; extra == "backend"
Dynamic: license-file
